setup.py
pDtlabCsCovea5/_init_.py
pDtlabCsCovea5.egg-info/PKG-INFO
pDtlabCsCovea5.egg-info/SOURCES.txt
pDtlabCsCovea5.egg-info/dependency_links.txt
pDtlabCsCovea5.egg-info/not-zip-safe
pDtlabCsCovea5.egg-info/top_level.txt